meldutils/__init__.py
meldutils/__main__.py
meldutils/base.py
meldutils/tests/conftest.py
meldutils/tests/test_all.py
meldutils-2.3.0.dist-info/licenses/LICENSE.txt
meldutils-2.3.0.dist-info/METADATA
meldutils-2.3.0.dist-info/WHEEL
meldutils-2.3.0.dist-info/top_level.txt
meldutils-2.3.0.dist-info/RECORD
